fileboxes/__init__.py
fileboxes/custom_json_config/__init__.py
fileboxes/custom_json_config/custom_json_decoder.py
fileboxes/custom_json_config/custom_json_encoder.py
fileboxes/filebox.py
fileboxes/zipio.py
fileboxes-0.1.4.dist-info/METADATA
fileboxes-0.1.4.dist-info/WHEEL
fileboxes-0.1.4.dist-info/RECORD
