Metadata-Version: 2.1
Name: fileboxes
Version: 0.1.4
Summary: Simplifies the creation of custom formats.
Author: André Fernandes
Author-email: fpf.andre@gmail.com
Requires-Python: >=3.10
Classifier: Programming Language :: Python :: 3
Classifier: Programming Language :: Python :: 3.10
Classifier: Programming Language :: Python :: 3.11
Requires-Dist: numpy (>=1.26)
Requires-Dist: pillow (>=11.0.0,<12.0.0)
Requires-Dist: treelib (>=1.7.0,<2.0.0)
